pym3u8downloader/__init__.py
pym3u8downloader/downloader.py
pym3u8downloader/exceptions.py
pym3u8downloader/utility_class.py
pym3u8downloader/validations.py
pym3u8downloader-0.1.8.dist-info/LICENSE
pym3u8downloader-0.1.8.dist-info/METADATA
pym3u8downloader-0.1.8.dist-info/WHEEL
pym3u8downloader-0.1.8.dist-info/top_level.txt
pym3u8downloader-0.1.8.dist-info/RECORD
