Metadata-Version: 2.1
Name: pym3u8downloader
Version: 0.1.8
Summary: M3U8 Downloader is a Python class designed to download and concatenate video files from M3U8 playlists.
Home-page: https://github.com/coldsofttech/pym3u8downloader
Author: coldsofttech
License: MIT
Keywords: m3u8-playlist,m3u8,m3u8-downloader
Classifier: Development Status :: 4 - Beta
Classifier: Intended Audience :: Developers
Classifier: Topic :: Software Development :: Libraries :: Python Modules
Classifier: Topic :: Multimedia :: Video
Classifier: License :: OSI Approved :: MIT License
Classifier: Programming Language :: Python :: 3.10
Classifier: Programming Language :: Python :: 3.11
Classifier: Programming Language :: Python :: 3.12
License-File: LICENSE
Requires-Dist: requests
Requires-Dist: pyloggermanager
